gpt_code_generator/__init__.py
gpt_code_generator/args/__init__.py
gpt_code_generator/args/args.py
gpt_code_generator/args/env.py
gpt_code_generator/generator.py
gpt_code_generator/llama_index_wrapper/__init__.py
gpt_code_generator/llama_index_wrapper/api.py
gpt_code_generator/llama_index_wrapper/github.py
gpt_code_generator/save.py
gpt_code_generator/storage/__init__.py
gpt_code_generator/storage/storage.py
gpt_code_generator/zip/__init__.py
gpt_code_generator/zip/zip.py
gpt_code_generator-0.1.1.dist-info/METADATA
gpt_code_generator-0.1.1.dist-info/WHEEL
gpt_code_generator-0.1.1.dist-info/entry_points.txt
gpt_code_generator-0.1.1.dist-info/RECORD
